pdfminer/__init__.py
pdfminer/arcfour.py
pdfminer/ascii85.py
pdfminer/ccitt.py
pdfminer/cmapdb.py
pdfminer/converter.py
pdfminer/encodingdb.py
pdfminer/fontmetrics.py
pdfminer/glyphlist.py
pdfminer/image.py
pdfminer/latin_enc.py
pdfminer/layout.py
pdfminer/lzw.py
pdfminer/pdfcolor.py
pdfminer/pdfdevice.py
pdfminer/pdfdocument.py
pdfminer/pdffont.py
pdfminer/pdfinterp.py
pdfminer/pdfpage.py
pdfminer/pdfparser.py
pdfminer/pdftypes.py
pdfminer/psparser.py
pdfminer/rijndael.py
pdfminer/runlength.py
pdfminer/utils.py
pdfminer/cmap/78-EUC-H.marshal.gz
pdfminer/cmap/78-EUC-V.marshal.gz
pdfminer/cmap/78-H.marshal.gz
pdfminer/cmap/78-RKSJ-H.marshal.gz
pdfminer/cmap/78-RKSJ-V.marshal.gz
pdfminer/cmap/78-V.marshal.gz
pdfminer/cmap/78ms-RKSJ-H.marshal.gz
pdfminer/cmap/78ms-RKSJ-V.marshal.gz
pdfminer/cmap/83pv-RKSJ-H.marshal.gz
pdfminer/cmap/83pv-RKSJ-V.marshal.gz
pdfminer/cmap/90ms-RKSJ-H.marshal.gz
pdfminer/cmap/90ms-RKSJ-V.marshal.gz
pdfminer/cmap/90msp-RKSJ-H.marshal.gz
pdfminer/cmap/90msp-RKSJ-V.marshal.gz
pdfminer/cmap/90pv-RKSJ-H.marshal.gz
pdfminer/cmap/90pv-RKSJ-V.marshal.gz
pdfminer/cmap/Add-H.marshal.gz
pdfminer/cmap/Add-RKSJ-H.marshal.gz
pdfminer/cmap/Add-RKSJ-V.marshal.gz
pdfminer/cmap/Add-V.marshal.gz
pdfminer/cmap/B5-H.marshal.gz
pdfminer/cmap/B5-V.marshal.gz
pdfminer/cmap/B5pc-H.marshal.gz
pdfminer/cmap/B5pc-V.marshal.gz
pdfminer/cmap/CNS-EUC-H.marshal.gz
pdfminer/cmap/CNS-EUC-V.marshal.gz
pdfminer/cmap/CNS1-H.marshal.gz
pdfminer/cmap/CNS1-V.marshal.gz
pdfminer/cmap/CNS2-H.marshal.gz
pdfminer/cmap/CNS2-V.marshal.gz
pdfminer/cmap/ETHK-B5-H.marshal.gz
pdfminer/cmap/ETHK-B5-V.marshal.gz
pdfminer/cmap/ETen-B5-H.marshal.gz
pdfminer/cmap/ETen-B5-V.marshal.gz
pdfminer/cmap/ETenms-B5-H.marshal.gz
pdfminer/cmap/ETenms-B5-V.marshal.gz
pdfminer/cmap/EUC-H.marshal.gz
pdfminer/cmap/EUC-V.marshal.gz
pdfminer/cmap/Ext-H.marshal.gz
pdfminer/cmap/Ext-RKSJ-H.marshal.gz
pdfminer/cmap/Ext-RKSJ-V.marshal.gz
pdfminer_with_logger-1.0.0.dist-info/DESCRIPTION.rst
pdfminer_with_logger-1.0.0.dist-info/METADATA
pdfminer_with_logger-1.0.0.dist-info/RECORD
pdfminer_with_logger-1.0.0.dist-info/WHEEL
pdfminer_with_logger-1.0.0.dist-info/metadata.json
pdfminer_with_logger-1.0.0.dist-info/top_level.txt
