Metadata-Version: 2.0
Name: pdfminer-with-logger
Version: 1.0.0
Summary: PDF parser and analyzer
Home-page: http://github.com/euske/pdfminer
Author: Yusuke Shinyama
Author-email: yusuke@shinyama.jp
License: MIT
Keywords: pdf parser,pdf converter,layout analysis,text mining
Platform: UNKNOWN
Classifier: Development Status :: 4 - Beta
Classifier: Environment :: Console
Classifier: Intended Audience :: Developers
Classifier: Intended Audience :: Science/Research
Classifier: License :: OSI Approved :: MIT License
Classifier: Topic :: Text Processing
Requires-Python: >=3.6
Requires-Dist: pycryptodome
